doc/Makefile
doc/conf.py
doc/index.rst
doc/source/api.views.rst
doc/source/authentication.md
doc/source/decorator.md
doc/source/generate_openapi.md
doc/source/getting_started.md
doc/source/internationalisation.md
doc/source/model.md
doc/source/pfx_views.md
doc/source/profiling.md
doc/source/settings.md
doc/source/testing.md
pfx/__init__.py
pfx/pfxcore/__init__.py
pfx/pfxcore/apps.py
pfx/pfxcore/default_settings.py
pfx/pfxcore/exceptions.py
pfx/pfxcore/fields.py
pfx/pfxcore/settings.py
pfx/pfxcore/shortcuts.py
pfx/pfxcore/test.py
pfx/pfxcore/urls.py
pfx/pfxcore/apidoc/__init__.py
pfx/pfxcore/apidoc/parameters.py
pfx/pfxcore/apidoc/schema.py
pfx/pfxcore/apidoc/tags.py
pfx/pfxcore/decorator/__init__.py
pfx/pfxcore/decorator/rest.py
pfx/pfxcore/http/__init__.py
pfx/pfxcore/http/json_response.py
pfx/pfxcore/locale/fr/LC_MESSAGES/django.mo
pfx/pfxcore/locale/fr/LC_MESSAGES/django.po
pfx/pfxcore/management/__init__.py
pfx/pfxcore/management/commands/__init__.py
pfx/pfxcore/management/commands/makeapidoc.py
pfx/pfxcore/management/commands/profile.py
pfx/pfxcore/middleware/__init__.py
pfx/pfxcore/middleware/authentication.py
pfx/pfxcore/middleware/locale.py
pfx/pfxcore/middleware/profiling.py
pfx/pfxcore/models/__init__.py
pfx/pfxcore/models/cache_mixins.py
pfx/pfxcore/models/not_null_fields.py
pfx/pfxcore/models/pfx_models.py
pfx/pfxcore/models/user_filtered_queryset_mixin.py
pfx/pfxcore/serializers/__init__.py
pfx/pfxcore/serializers/json.py
pfx/pfxcore/storage/__init__.py
pfx/pfxcore/storage/s3_storage.py
pfx/pfxcore/templates/registration/password_reset_email.txt
pfx/pfxcore/templates/registration/password_reset_subject.txt
pfx/pfxcore/templates/registration/welcome_email.txt
pfx/pfxcore/templates/registration/welcome_subject.txt
pfx/pfxcore/views/__init__.py
pfx/pfxcore/views/authentication_views.py
pfx/pfxcore/views/fields.py
pfx/pfxcore/views/filters_views.py
pfx/pfxcore/views/locale_views.py
pfx/pfxcore/views/rest_views.py
pfx/pfxcore/views/parameters/__init__.py
django_pfx-1.3.dist-info/LICENSE
django_pfx-1.3.dist-info/METADATA
django_pfx-1.3.dist-info/WHEEL
django_pfx-1.3.dist-info/top_level.txt
django_pfx-1.3.dist-info/RECORD
